zope/globalrequest/__init__.py
zope/globalrequest/configure.zcml
zope/globalrequest/interfaces.py
zope/globalrequest/local.py
zope/globalrequest/subscribers.py
zope/globalrequest/tests.py
zope_globalrequest-3.0.dist-info/METADATA
zope_globalrequest-3.0.dist-info/WHEEL
zope_globalrequest-3.0.dist-info/top_level.txt
zope_globalrequest-3.0.dist-info/RECORD
